{
    "created_at":"Mon Mar 02 02:57:02 +0000 2020",
    "id":1234311726528516097,
    "id_str":"1234311726528516097",
    "text":"@macaron_309 \u30b5\u30c3\u30af\u30b9\u306f\u6728\u7ba1\u697d\u5668\u306a\u306e\u306b\u91d1\u5c5e\u3067\u3067\u304d\u3066\u307e\u3059\u304b\u3089\u306d(\u00b4\u30fb\u03c9\u30fb\uff40)",
    "display_text_range":[13,43],
    "source":"\u003ca href=\"http:\/\/twitter.com\/download\/android\" rel=\"nofollow\"\u003eTwitter for Android\u003c\/a\u003e",
    "truncated":false,
    "in_reply_to_status_id":1234249317579276288,
    "in_reply_to_status_id_str":"1234249317579276288",
    "in_reply_to_user_id":1138714274753175552,
    "in_reply_to_user_id_str":"1138714274753175552",
    "in_reply_to_screen_name":"macaron_309",
    "user":{
        "id":1192060149688455168,
        "id_str":"1192060149688455168",
        "name":"TOKAGE",
        "screen_name":"TOKAGE75073",
        "location":"\u7530\u820e\u306e\u90fd\u4f1a",
        "url":null,
        "description":"\u30fb\u9ad8\u6821\u751f\n\u30fb\u306b\u3083\u3093\u3053\u5927\u6226\u4e89\n\u30fb\u81ea\u4f5cer\n\u30fb\u30ab\u30e1\u30e9\u597d\u304d\u306a\u30ab\u30e1\u30e9\u521d\u5fc3\u8005\n\u30fb\u30ac\u30b8\u30a7\u30c3\u30bf\u30fc\n\u30fb\u30d5\u30a9\u30ed\u30d0100\uff05\u3089\u3057\u3044\n\u540d\u4ed8\u3051\u89aa\u2192\uff20TERESA10191797",
        "translator_type":"none",
        "protected":false,
        "verified":false,
        "followers_count":31,
        "friends_count":56,
        "listed_count":0,
        "favourites_count":1978,
        "statuses_count":331,
        "created_at":"Wed Nov 06 12:44:36 +0000 2019",
        "utc_offset":null,
        "time_zone":null,
        "geo_enabled":false,
        "lang":null,
        "contributors_enabled":false,
        "is_translator":false,
        "profile_background_color":"F5F8FA",
        "profile_background_image_url":"",
        "profile_background_image_url_https":"",
        "profile_background_tile":false,
        "profile_link_color":"1DA1F2",
        "profile_sidebar_border_color":"C0DEED",
        "profile_sidebar_fill_color":"DDEEF6",
        "profile_text_color":"333333",
        "profile_use_background_image":true,
        "profile_image_url":"http:\/\/pbs.twimg.com\/profile_images\/1233715890945835008\/mhjSlfFy_normal.jpg",
        "profile_image_url_https":"https:\/\/pbs.twimg.com\/profile_images\/1233715890945835008\/mhjSlfFy_normal.jpg",
        "default_profile":true,
        "default_profile_image":false,
        "following":null,
        "follow_request_sent":null,
        "notifications":null
    },
    "geo":null,
    "coordinates":null,
    "place":null,
    "contributors":null,
    "is_quote_status":false,
    "quote_count":0,
    "reply_count":0,
    "retweet_count":0,
    "favorite_count":0,
    "entities":{
        "hashtags":[],
        "urls":[],
        "user_mentions":[{
            "screen_name":"macaron_309",
            "name":"\u307e\u304b\u308d\u3093\u81ea\u4f5cer",
            "id":1138714274753175552,
            "id_str":"1138714274753175552",
            "indices":[0,12]
        }],
        "symbols":[]
    },
    "favorited":false,
    "retweeted":false,
    "filter_level":"low",
    "lang":"ja",
    "timestamp_ms":"1583117822664"
}